optuna_distributed/__init__.py
optuna_distributed/config.py
optuna_distributed/eventloop.py
optuna_distributed/py.typed
optuna_distributed/study.py
optuna_distributed/terminal.py
optuna_distributed/trial.py
optuna_distributed/ipc/__init__.py
optuna_distributed/ipc/base.py
optuna_distributed/ipc/pipe.py
optuna_distributed/ipc/queue.py
optuna_distributed/managers/__init__.py
optuna_distributed/managers/base.py
optuna_distributed/managers/distributed.py
optuna_distributed/managers/local.py
optuna_distributed/messages/__init__.py
optuna_distributed/messages/base.py
optuna_distributed/messages/completed.py
optuna_distributed/messages/failed.py
optuna_distributed/messages/heartbeat.py
optuna_distributed/messages/property.py
optuna_distributed/messages/pruned.py
optuna_distributed/messages/report.py
optuna_distributed/messages/response.py
optuna_distributed/messages/setattr.py
optuna_distributed/messages/shouldprune.py
optuna_distributed/messages/suggest.py
optuna_distributed-0.7.0.dist-info/LICENSE
optuna_distributed-0.7.0.dist-info/METADATA
optuna_distributed-0.7.0.dist-info/WHEEL
optuna_distributed-0.7.0.dist-info/top_level.txt
optuna_distributed-0.7.0.dist-info/RECORD
