Metadata-Version: 2.1
Name: optuna-distributed
Version: 0.7.0
Summary: Distributed hyperparameter optimization made easy
Author-email: Adrian Zuber <xadrianzetx@gmail.com>
License: MIT
Project-URL: Source, https://github.com/xadrianzetx/optuna-distributed
Project-URL: Bug Tracker, https://github.com/xadrianzetx/optuna-distributed/issues
Classifier: Development Status :: 4 - Beta
Classifier: Intended Audience :: Science/Research
Classifier: Intended Audience :: Developers
Classifier: License :: OSI Approved :: MIT License
Classifier: Programming Language :: Python :: 3
Classifier: Programming Language :: Python :: 3.8
Classifier: Programming Language :: Python :: 3.9
Classifier: Programming Language :: Python :: 3.10
Classifier: Programming Language :: Python :: 3.11
Classifier: Programming Language :: Python :: 3.12
Classifier: Programming Language :: Python :: 3 :: Only
Classifier: Topic :: Scientific/Engineering
Classifier: Topic :: Scientific/Engineering :: Mathematics
Classifier: Topic :: Scientific/Engineering :: Artificial Intelligence
Classifier: Topic :: Software Development
Classifier: Topic :: Software Development :: Libraries
Classifier: Topic :: Software Development :: Libraries :: Python Modules
Classifier: Topic :: System :: Distributed Computing
Requires-Python: >=3.8
License-File: LICENSE
Requires-Dist: optuna >=3.1.0
Requires-Dist: dask[distributed]
Requires-Dist: rich
Provides-Extra: dev
Requires-Dist: black ; extra == 'dev'
Requires-Dist: isort ; extra == 'dev'
Requires-Dist: flake8 ; extra == 'dev'
Requires-Dist: mypy ; extra == 'dev'
Requires-Dist: pandas ; extra == 'dev'
Requires-Dist: pandas-stubs ; extra == 'dev'
Provides-Extra: test
Requires-Dist: pytest ; extra == 'test'
